cancel_token/__init__.py
cancel_token/cancel_token.py
cancel_token/py.typed
cancel_token-0.1.6.dist-info/LICENSE
cancel_token-0.1.6.dist-info/METADATA
cancel_token-0.1.6.dist-info/WHEEL
cancel_token-0.1.6.dist-info/top_level.txt
cancel_token-0.1.6.dist-info/RECORD
