Metadata-Version: 2.1
Name: cancel-token
Version: 0.1.6
Summary: Simple CancellationToken
Home-page: https://github.com/Novakov/py-cancel-token
Author: Maciej Nowak
License: UNKNOWN
Platform: UNKNOWN
Classifier: Programming Language :: Python :: 2
Classifier: Programming Language :: Python :: 3
Classifier: License :: OSI Approved :: MIT License
Classifier: Operating System :: OS Independent
Classifier: Development Status :: 3 - Alpha
Classifier: Intended Audience :: Developers
Classifier: Topic :: Utilities
